emptool/__init__.py
emptool/cli.py
emptool/emptool.py
emptool/pypi.py
emptool/rawrepl.py
emptool-0.9.7.dist-info/AUTHORS
emptool-0.9.7.dist-info/LICENSE
emptool-0.9.7.dist-info/METADATA
emptool-0.9.7.dist-info/WHEEL
emptool-0.9.7.dist-info/entry_points.txt
emptool-0.9.7.dist-info/pbr.json
emptool-0.9.7.dist-info/top_level.txt
emptool-0.9.7.dist-info/RECORD
