Metadata-Version: 2.1
Name: emptool
Version: 0.9.7
Summary: Easy MicroPython toolchain
Home-page: https://github.com/Easy-MicroPython
Author: Singein
Author-email: singein@outlook.com
License: MIT
Platform: UNKNOWN
Classifier: Development Status :: 4 - Beta
Classifier: Environment :: Console
Classifier: Environment :: OpenStack
Classifier: Intended Audience :: Developers
Classifier: Intended Audience :: Information Technology
Classifier: License :: OSI Approved :: Apache Software License
Classifier: Operating System :: OS Independent
Classifier: Programming Language :: Python
Requires-Dist: fire
Requires-Dist: pyserial
Requires-Dist: osprofile
Requires-Dist: requests
